tokentrim/__init__.py
tokentrim/model_map.py
tokentrim/tokentrim.py
tokentrim-0.1.11.dist-info/LICENSE
tokentrim-0.1.11.dist-info/METADATA
tokentrim-0.1.11.dist-info/WHEEL
tokentrim-0.1.11.dist-info/RECORD
