Metadata-Version: 2.1
Name: tokentrim
Version: 0.1.11
Summary: Easily trim 'messages' arrays for use with GPTs.
Author: Killian Lucas
Author-email: killian@drinkwater.ai
Requires-Python: >=3.8,<4.0
Classifier: Programming Language :: Python :: 3
Classifier: Programming Language :: Python :: 3.8
Classifier: Programming Language :: Python :: 3.9
Classifier: Programming Language :: Python :: 3.10
Classifier: Programming Language :: Python :: 3.11
Requires-Dist: tiktoken (>=0.4.0,<0.5.0)
